debugBuddy/__init__.py
debugBuddy/__main__.py
debugBuddy/cli.py
debugBuddy/debug.py
debugBuddy/example.py
debugbuddy-0.0.0.dist-info/licenses/LICENSE
debugbuddy-0.0.0.dist-info/METADATA
debugbuddy-0.0.0.dist-info/WHEEL
debugbuddy-0.0.0.dist-info/entry_points.txt
debugbuddy-0.0.0.dist-info/top_level.txt
debugbuddy-0.0.0.dist-info/RECORD
