Metadata-Version: 2.4
Name: debugBuddy
Version: 0.0.0
Summary: A python package that gives you general tips and encouragement when debugging your file!
Author-email: Samir Hussain <sh6888@nyu.edu>, Jake Chang <jc11229@nyu.edu>, Jimena Menendez <jkm8294@nyu.edu>, Sarah Wang <ssw8645@nyu.edu>
License:                     GNU GENERAL PUBLIC LICENSE
Project-URL: Homepage, https://github.com/software-students-spring2025/3-python-package-p3-py
Project-URL: Repository, https://github.com/software-students-spring2025/3-python-package-p3-py.git
Project-URL: Bug Tracker, https://github.com/software-students-spring2025/3-python-package-p3-py/issues
Keywords: python,package,debugging
Classifier: Programming Language :: Python :: 3
Classifier: License :: OSI Approved :: GNU General Public License v3 (GPLv3)
Classifier: Operating System :: OS Independent
Requires-Python: >=3.7
License-File: LICENSE
Provides-Extra: dev
Requires-Dist: pytest; extra == "dev"
Dynamic: license-file
